mahonia/__init__.py
mahonia/latex.py
mahonia/py.typed
mahonia/stats.py
mahonia-0.3.0.dist-info/METADATA
mahonia-0.3.0.dist-info/WHEEL
mahonia-0.3.0.dist-info/licenses/LICENSE
mahonia-0.3.0.dist-info/RECORD
