Metadata-Version: 2.4
Name: mahonia
Version: 0.3.0
Summary: Mahonia is a domain specific language (DSL) for defining, evaluating, saving, and serializing binary expressions.
Author-email: JP Hutchins <jphutchins@gmail.com>
License: MIT License
License-File: LICENSE
Requires-Python: >=3.12
